wiotp_sdk-1.0.1-py3.12-nspkg.pth
wiotp/sdk/__init__.py
wiotp/sdk/client.py
wiotp/sdk/exceptions.py
wiotp/sdk/messages.py
wiotp/sdk/messaging.pem
wiotp/sdk/api/__init__.py
wiotp/sdk/api/common.py
wiotp/sdk/api/actions/__init__.py
wiotp/sdk/api/actions/actions.py
wiotp/sdk/api/actions/triggers.py
wiotp/sdk/api/dsc/__init__.py
wiotp/sdk/api/dsc/connectors.py
wiotp/sdk/api/dsc/destinations.py
wiotp/sdk/api/dsc/forwarding.py
wiotp/sdk/api/lec/__init__.py
wiotp/sdk/api/mgmt/__init__.py
wiotp/sdk/api/mgmt/extensions.py
wiotp/sdk/api/mgmt/requests.py
wiotp/sdk/api/registry/__init__.py
wiotp/sdk/api/registry/connectionStatus.py
wiotp/sdk/api/registry/devices.py
wiotp/sdk/api/registry/diag.py
wiotp/sdk/api/registry/types.py
wiotp/sdk/api/services/__init__.py
wiotp/sdk/api/services/credentials.py
wiotp/sdk/api/state/__init__.py
wiotp/sdk/api/state/deviceTypes.py
wiotp/sdk/api/state/devices.py
wiotp/sdk/api/state/eventTypes.py
wiotp/sdk/api/state/logicalInterfaces.py
wiotp/sdk/api/state/physicalInterfaces.py
wiotp/sdk/api/state/rules.py
wiotp/sdk/api/state/schemas.py
wiotp/sdk/api/state/state.py
wiotp/sdk/api/state/thingState.py
wiotp/sdk/api/state/thingTypes.py
wiotp/sdk/api/state/things.py
wiotp/sdk/api/status/__init__.py
wiotp/sdk/api/usage/__init__.py
wiotp/sdk/application/__init__.py
wiotp/sdk/application/client.py
wiotp/sdk/application/config.py
wiotp/sdk/application/messages.py
wiotp/sdk/device/__init__.py
wiotp/sdk/device/client.py
wiotp/sdk/device/command.py
wiotp/sdk/device/config.py
wiotp/sdk/device/deviceFirmware.py
wiotp/sdk/device/deviceInfo.py
wiotp/sdk/device/managedClient.py
wiotp/sdk/gateway/__init__.py
wiotp/sdk/gateway/client.py
wiotp/sdk/gateway/config.py
wiotp/sdk/gateway/managedClient.py
wiotp/sdk/gateway/messages.py
wiotp_sdk-1.0.1.data/scripts/wiotp-cli
wiotp_sdk-1.0.1.dist-info/LICENSE
wiotp_sdk-1.0.1.dist-info/METADATA
wiotp_sdk-1.0.1.dist-info/WHEEL
wiotp_sdk-1.0.1.dist-info/namespace_packages.txt
wiotp_sdk-1.0.1.dist-info/top_level.txt
wiotp_sdk-1.0.1.dist-info/RECORD
