Metadata-Version: 2.1
Name: wiotp-sdk
Version: 1.0.1
Summary: Python SDK for Maximo IoT and IBM Watson IoT Platform
Home-page: https://github.com/ibm-watson-iot/iot-python
Author: David Parker
Author-email: parkerda@uk.ibm.com
License: Eclipse Public License - v1.0
Classifier: Development Status :: 4 - Beta
Classifier: Intended Audience :: Developers
Classifier: Operating System :: Microsoft :: Windows
Classifier: Operating System :: POSIX :: Linux
Classifier: Programming Language :: Python
Classifier: Programming Language :: Python :: 3.9
Classifier: Programming Language :: Python :: 3.10
Classifier: Programming Language :: Python :: 3.11
Classifier: Topic :: Communications
Classifier: Topic :: Internet
Classifier: Topic :: Software Development :: Libraries :: Python Modules
License-File: LICENSE
Requires-Dist: iso8601 >=0.1.12
Requires-Dist: pytz >=2020.1
Requires-Dist: pyyaml >=5.3.1
Requires-Dist: paho-mqtt <2.0.0,>=1.5.0
Requires-Dist: requests >=2.23.0
Requires-Dist: requests-toolbelt >=0.9.1
Provides-Extra: dev
Requires-Dist: build ; extra == 'dev'
Requires-Dist: pytest ; extra == 'dev'
